<annotation><filename>363.jpg</filename><folder>onlybbhuman</folder><source><sourceImage>The ICG Semantic Drone Dataset</sourceImage><sourceAnnotation>LabelMe Webtool</sourceAnnotation></source><object><name>person</name><deleted>0</deleted><verified>1</verified><occluded>no</occluded><attributes /><parts><hasparts /><ispartof /></parts><date>06-Jul-2017 12:43:01</date><id>0</id><type>bounding_box</type><polygon><username>sara</username><pt><x>1757</x><y>3518</y></pt><pt><x>2100</x><y>3518</y></pt><pt><x>2100</x><y>3846</y></pt><pt><x>1757</x><y>3846</y></pt></polygon></object><object><name>person</name><deleted>0</deleted><verified>1</verified><occluded>no</occluded><attributes /><parts><hasparts /><ispartof /></parts><date>06-Jul-2017 12:43:22</date><id>1</id><type>bounding_box</type><polygon><username>sara</username><pt><x>2433</x><y>3820</y></pt><pt><x>1866</x><y>3820</y></pt><pt><x>1866</x><y>3368</y></pt><pt><x>2433</x><y>3368</y></pt></polygon></object><object><name>person</name><deleted>0</deleted><verified>1</verified><occluded>yes</occluded><attributes /><parts><hasparts /><ispartof /></parts><date>06-Jul-2017 12:43:46</date><id>2</id><type>bounding_box</type><polygon><username>sara</username><pt><x>3779</x><y>3558</y></pt><pt><x>4141</x><y>3558</y></pt><pt><x>4141</x><y>3999</y></pt><pt><x>3779</x><y>3999</y></pt></polygon></object><object><name>person</name><deleted>0</deleted><verified>1</verified><occluded>no</occluded><attributes /><parts><hasparts /><ispartof /></parts><date>06-Jul-2017 12:44:05</date><id>3</id><type>bounding_box</type><polygon><username>sara</username><pt><x>4092</x><y>3324</y></pt><pt><x>4439</x><y>3324</y></pt><pt><x>4439</x><y>3808</y></pt><pt><x>4092</x><y>3808</y></pt></polygon></object><object><name>person</name><deleted>0</deleted><verified>1</verified><occluded>no</occluded><attributes /><parts><hasparts /><ispartof /></parts><date>06-Jul-2017 12:44:33</date><id>4</id><type>bounding_box</type><polygon><username>sara</username><pt><x>4875</x><y>1848</y></pt><pt><x>5456</x><y>1848</y></pt><pt><x>5456</x><y>1509</y></pt><pt><x>4875</x><y>1509</y></pt></polygon></object><object><name>person</name><deleted>0</deleted><verified>1</verified><occluded>no</occluded><attributes /><parts><hasparts /><ispartof /></parts><date>06-Jul-2017 12:45:02</date><id>5</id><type>bounding_box</type><polygon><username>sara</username><pt><x>4617</x><y>1254</y></pt><pt><x>5004</x><y>1254</y></pt><pt><x>5004</x><y>1681</y></pt><pt><x>4617</x><y>1681</y></pt></polygon></object><object><name>person</name><deleted>0</deleted><verified>1</verified><occluded>no</occluded><attributes /><parts><hasparts /><ispartof /></parts><date>06-Jul-2017 12:45:50</date><id>6</id><type>bounding_box</type><polygon><username>sara</username><pt><x>3862</x><y>1321</y></pt><pt><x>4251</x><y>1321</y></pt><pt><x>4251</x><y>1648</y></pt><pt><x>3862</x><y>1648</y></pt></polygon></object><object><name>person</name><deleted>0</deleted><verified>1</verified><occluded /><attributes /><parts><hasparts /><ispartof /></parts><date>06-Jul-2017 12:46:16</date><id>7</id><type>bounding_box</type><polygon><username>sara</username><pt><x>3894</x><y>960</y></pt><pt><x>4343</x><y>960</y></pt><pt><x>4343</x><y>1393</y></pt><pt><x>3894</x><y>1393</y></pt></polygon></object><imagesize><nrows>4000</nrows><ncols>6000</ncols></imagesize></annotation>