<annotation><filename>1465462e2aa44c3a8b6b93e4b9e3ec16420.jpg</filename><folder>testbatchdb6094cf65664e21bfda09ca139ac4af</folder><source><sourceImage>The MIT-CSAIL database of objects and scenes</sourceImage><sourceAnnotation>LabelMe Webtool</sourceAnnotation><layerCount>1</layerCount></source><layerCount>0</layerCount><object><name>grass</name><deleted>0</deleted><verified>0</verified><occluded>no</occluded><attributes></attributes><parts><hasparts></hasparts><ispartof>1</ispartof></parts><date>19-Apr-2018 14:58:37</date><id>0</id><polygon><username>AWS816ff6f8b435706086db</username><pt><x>0</x><y>15</y></pt><pt><x>10</x><y>4000</y></pt><pt><x>5997</x><y>3990</y></pt><pt><x>5997</x><y>15</y></pt></polygon></object><object><name>layer</name><deleted>0</deleted><verified>0</verified><occluded></occluded><attributes>0</attributes><parts><hasparts>0</hasparts><ispartof></ispartof></parts><date>19-Apr-2018 14:58:40</date><id>1</id><polygon><username>AWS816ff6f8b435706086db</username></polygon></object><imagesize><nrows></nrows><ncols></ncols></imagesize></annotation>